lingvanex_API/__init__.py
lingvanex_API/get_languages.py
lingvanex_API/translate.py
lingvanex-0.0.11.dist-info/METADATA
lingvanex-0.0.11.dist-info/WHEEL
lingvanex-0.0.11.dist-info/top_level.txt
lingvanex-0.0.11.dist-info/RECORD
