Metadata-Version: 2.1
Name: lingvanex
Version: 0.0.11
Summary: Lingvanex API instructions
Author-email: Lingvanex <tech@lingvanex.com>
Project-URL: Homepage, https://github.com/lingvanex-mt
Project-URL: Issues, https://github.com/lingvanex-mt
Classifier: Programming Language :: Python :: 3
Classifier: License :: OSI Approved :: MIT License
Classifier: Operating System :: OS Independent
Requires-Python: >=3.8
Requires-Dist: requests (>=2.32.1)
